cubicweb_web/__init__.py
cubicweb_web/__pkginfo__.py
cubicweb_web/_exceptions.py
cubicweb_web/action.py
cubicweb_web/application.py
cubicweb_web/box.py
cubicweb_web/bwcompat.py
cubicweb_web/captcha.py
cubicweb_web/ccplugin.py
cubicweb_web/component.py
cubicweb_web/controller.py
cubicweb_web/facet.py
cubicweb_web/form.py
cubicweb_web/formfields.py
cubicweb_web/formwidgets.py
cubicweb_web/htmlwidgets.py
cubicweb_web/http_headers.py
cubicweb_web/httpcache.py
cubicweb_web/i18n.py
cubicweb_web/predicates.py
cubicweb_web/propertysheet.py
cubicweb_web/request.py
cubicweb_web/schemaviewer.py
cubicweb_web/tags.py
cubicweb_web/uihelper.py
cubicweb_web/utils.py
cubicweb_web/view.py
cubicweb_web/webconfig.py
cubicweb_web/data/accessories-text-editor.png
cubicweb_web/data/add_button.png
cubicweb_web/data/asc.gif
cubicweb_web/data/banner.png
cubicweb_web/data/bg.gif
cubicweb_web/data/bg_trame_grise.png
cubicweb_web/data/black-check.png
cubicweb_web/data/black-uncheck.png
cubicweb_web/data/bullet.png
cubicweb_web/data/bullet_orange.png
cubicweb_web/data/button.png
cubicweb_web/data/calendar.gif
cubicweb_web/data/cancel.png
cubicweb_web/data/contextFreeBoxHeader.png
cubicweb_web/data/contextualBoxHeader.png
cubicweb_web/data/critical.png
cubicweb_web/data/cubicweb.acl.css
cubicweb_web/data/cubicweb.ajax.box.js
cubicweb_web/data/cubicweb.ajax.js
cubicweb_web/data/cubicweb.calendar.css
cubicweb_web/data/cubicweb.calendar.js
cubicweb_web/data/cubicweb.calendar_popup.css
cubicweb_web/data/cubicweb.compat.js
cubicweb_web/data/cubicweb.css
cubicweb_web/data/cubicweb.edition.js
cubicweb_web/data/cubicweb.facets.css
cubicweb_web/data/cubicweb.facets.js
cubicweb_web/data/cubicweb.fckcwconfig-full.js
cubicweb_web/data/cubicweb.fckcwconfig.js
cubicweb_web/data/cubicweb.flot.js
cubicweb_web/data/cubicweb.form.css
cubicweb_web/data/cubicweb.html_tree.css
cubicweb_web/data/cubicweb.htmlhelpers.js
cubicweb_web/data/cubicweb.ie.css
cubicweb_web/data/cubicweb.image.js
cubicweb_web/data/cubicweb.js
cubicweb_web-1.6.2.dist-info/METADATA
cubicweb_web-1.6.2.dist-info/WHEEL
cubicweb_web-1.6.2.dist-info/entry_points.txt
cubicweb_web-1.6.2.dist-info/top_level.txt
cubicweb_web-1.6.2.dist-info/RECORD
