Metadata-Version: 2.4
Name: cubicweb-web
Version: 1.6.2
Summary: Legacy component for web application
Author-email: Logilab <contact@logilab.fr>
License: GNU Lesser General Public License v2 or later (LGPLv2+)
Project-URL: Issues, https://forge.extranet.logilab.fr/cubicweb/cubes/web/-/issues
Project-URL: Repository, https://forge.extranet.logilab.fr/cubicweb/cubes/web
Classifier: Environment :: Web Environment
Classifier: Framework :: CubicWeb
Classifier: Programming Language :: Python
Classifier: Programming Language :: Python :: 3
Classifier: Programming Language :: Python :: 3 :: Only
Classifier: Programming Language :: JavaScript
Requires-Python: >=3.11
Requires-Dist: cubicweb<6.0.0,>=4.5.2
Requires-Dist: yams>=2.0.0
